pygameflow/__init__.py
pygameflow-0.0.0a1.dist-info/LICENSE
pygameflow-0.0.0a1.dist-info/METADATA
pygameflow-0.0.0a1.dist-info/WHEEL
pygameflow-0.0.0a1.dist-info/RECORD
